fooocusapi_client/__init__.py
fooocusapi_client/api_client.py
fooocusapi_client/api_response.py
fooocusapi_client/configuration.py
fooocusapi_client/exceptions.py
fooocusapi_client/py.typed
fooocusapi_client/rest.py
fooocusapi_client/api/__init__.py
fooocusapi_client/api/default_api.py
fooocusapi_client/models/__init__.py
fooocusapi_client/models/accept.py
fooocusapi_client/models/advanced_params.py
fooocusapi_client/models/all_model_names_response.py
fooocusapi_client/models/async_job_response.py
fooocusapi_client/models/async_job_stage.py
fooocusapi_client/models/cn_img.py
fooocusapi_client/models/cn_img1.py
fooocusapi_client/models/cn_stop.py
fooocusapi_client/models/cn_stop1.py
fooocusapi_client/models/cn_stop2.py
fooocusapi_client/models/cn_stop3.py
fooocusapi_client/models/cn_stop4.py
fooocusapi_client/models/cn_weight.py
fooocusapi_client/models/cn_weight1.py
fooocusapi_client/models/cn_weight2.py
fooocusapi_client/models/cn_weight3.py
fooocusapi_client/models/cn_weight4.py
fooocusapi_client/models/control_net_type.py
fooocusapi_client/models/describe_image_response.py
fooocusapi_client/models/describe_image_type.py
fooocusapi_client/models/generated_image_result.py
fooocusapi_client/models/generation_finish_reason.py
fooocusapi_client/models/http_validation_error.py
fooocusapi_client/models/image_prompt.py
fooocusapi_client/models/image_prompt_json.py
fooocusapi_client/models/img_inpaint_or_outpaint_request_json.py
fooocusapi_client/models/img_inpaint_or_outpaint_request_json_advanced_params.py
fooocusapi_client/models/img_inpaint_or_outpaint_request_json_image_prompts_inner.py
fooocusapi_client/models/img_prompt_request_json.py
fooocusapi_client/models/img_upscale_or_vary_request_json.py
fooocusapi_client/models/inpaint_additional_prompt.py
fooocusapi_client/models/inpaint_additional_prompt1.py
fooocusapi_client/models/input_image.py
fooocusapi_client/models/input_mask.py
fooocusapi_client/models/job_history_info.py
Fooocus_API_python_client-1.0.0.dist-info/LICENSE
Fooocus_API_python_client-1.0.0.dist-info/METADATA
Fooocus_API_python_client-1.0.0.dist-info/WHEEL
Fooocus_API_python_client-1.0.0.dist-info/top_level.txt
Fooocus_API_python_client-1.0.0.dist-info/RECORD
