Metadata-Version: 2.1
Name: Fooocus-API-python-client
Version: 1.0.0
Summary: FastAPI
Home-page: 
Author: OpenAPI Generator community
Author-email: team@openapitools.org
Keywords: OpenAPI,OpenAPI-Generator,FastAPI
License-File: LICENSE
Requires-Dist: urllib3 <2.1.0,>=1.25.3
Requires-Dist: python-dateutil
Requires-Dist: pydantic >=2
Requires-Dist: typing-extensions >=4.7.1
